pyross/__init__.py
pyross/contactMatrix.c
pyross/contactMatrix.cpython-310-darwin.so
pyross/contactMatrix.pyx
pyross/control.cpp
pyross/control.cpython-310-darwin.so
pyross/control.pyx
pyross/deterministic.c
pyross/deterministic.cpython-310-darwin.so
pyross/deterministic.pxd
pyross/deterministic.pyx
pyross/evidence.py
pyross/forecast.cpp
pyross/forecast.cpython-310-darwin.so
pyross/forecast.pyx
pyross/hybrid.cpp
pyross/hybrid.cpython-310-darwin.so
pyross/hybrid.pyx
pyross/inference.c
pyross/inference.cpython-310-darwin.so
pyross/inference.pyx
pyross/stochastic.cpp
pyross/stochastic.cpython-310-darwin.so
pyross/stochastic.pyx
pyross/tsi.py
pyross/utils.c
pyross/utils.cpython-310-darwin.so
pyross/utils.pyx
pyross/utils_python.py
pyross/tsi/__init__.py
pyross/tsi/deterministic.c
pyross/tsi/deterministic.cpython-310-darwin.so
pyross/tsi/deterministic.pyx
pyross-2.2.1.dist-info/LICENSE
pyross-2.2.1.dist-info/METADATA
pyross-2.2.1.dist-info/WHEEL
pyross-2.2.1.dist-info/top_level.txt
pyross-2.2.1.dist-info/RECORD
