Metadata-Version: 2.1
Name: pyross
Version: 2.2.1
Summary: PyRoss is a numerical library for inference, forecasts,                and optimal control of epidemiological models in Python
Home-page: https://github.com/rajeshrinet/pyross
Author: The PyRoss team
Author-email: pyross@googlegroups.com
License: MIT
Project-URL: Documentation, https://pyross.readthedocs.io
Project-URL: Source, https://github.com/rajeshrinet/pyross
Platform: tested on Linux
Platform: macOS
Platform: and windows
Classifier: License :: OSI Approved :: MIT License
Classifier: Programming Language :: Python :: 3
Classifier: Programming Language :: Python :: 3.7
Classifier: Topic :: Scientific/Engineering
Classifier: Topic :: Scientific/Engineering :: Mathematics
Classifier: Intended Audience :: Science/Research
Classifier: Intended Audience :: Education
License-File: LICENSE
Requires-Dist: cython
Requires-Dist: numpy
Requires-Dist: scipy
Requires-Dist: matplotlib
Requires-Dist: cma
Requires-Dist: sympy
Requires-Dist: nlopt
Requires-Dist: dill
